{
  "score": -2,
  "velocity": 0.17,
  "velocity_label": "급감 (×0.2)",
  "reason": "조회수 속도 급감 (×0.2) | 최근 3일 318,829회 / 이전 4~7일 1,878,157회 | 총 2,196,986회 (44개 영상)",
  "video_count": 44,
  "total_views": 2196986,
  "hot_views": 318829,
  "baseline_views": 1878157,
  "top_videos": [
    {
      "title": "손가락 모터 다 빼!&quot; 삼성 엔지니어들이 선택한 사람 힘줄(텐던)의 소름 돋는 비밀",
      "channel": "머스크의 모든 것",
      "publishedAt": "2026-06-01T08:22:31Z",
      "viewCount": 629103
    },
    {
      "title": "Yolopark Transformers Optimus Prime Stopmotion Build#transformers #stopmotion #optimusprime",
      "channel": "ZB Hobby",
      "publishedAt": "2026-06-03T04:50:25Z",
      "viewCount": 192709
    },
    {
      "title": "The iPhone Moment for Robots Just Happened",
      "channel": "Farzad",
      "publishedAt": "2026-06-01T12:00:39Z",
      "viewCount": 185206
    },
    {
      "title": "Elon Musk: This Will Be Bigger Than Cars #technology #elonmusk",
      "channel": "Macetarie",
      "publishedAt": "2026-06-04T19:30:08Z",
      "viewCount": 114302
    },
    {
      "title": "Elon Musk&#39;s First Prototype of Flying Tesla Robotaxi &quot;SkyCab&quot; Shocked the Industry",
      "channel": "Carros Show",
      "publishedAt": "2026-06-01T19:12:26Z",
      "viewCount": 79153
    }
  ],
  "collected_at": "2026-06-08T04:53:43Z"
}