{
  "score": -1,
  "velocity": 0.58,
  "velocity_label": "소폭 감소 (×0.6)",
  "reason": "조회수 속도 소폭 감소 (×0.6) | 최근 3일 345,780회 / 이전 4~7일 594,621회 | 총 940,401회 (45개 영상)",
  "video_count": 45,
  "total_views": 940401,
  "hot_views": 345780,
  "baseline_views": 594621,
  "top_videos": [
    {
      "title": "Transformers 7 Mein Unicorn Ne Human Form Kyu Nahi Liya  #shorts #optimusprime #transformers",
      "channel": "Mosh Brutal",
      "publishedAt": "2026-05-13T03:35:39Z",
      "viewCount": 67799
    },
    {
      "title": "Is Tesla About to Skyrocket? 5 Real Answers",
      "channel": "Brighter with Herbert",
      "publishedAt": "2026-05-11T13:30:38Z",
      "viewCount": 55694
    },
    {
      "title": "DRAM Stocks, Tesla, China, and Massive Volatility Coming Tomorrow",
      "channel": "StockedUp",
      "publishedAt": "2026-05-11T22:00:07Z",
      "viewCount": 47433
    },
    {
      "title": "Elon Musk: There Will Be More Robots Than People #elonmusk #tesla #spacex #optimus #grok #neuralink",
      "channel": "Beyond Ordinary ",
      "publishedAt": "2026-05-11T04:45:10Z",
      "viewCount": 46607
    },
    {
      "title": "40시간 째 일하는 모습 생중계 중… Figure 03 라이브가 보여준 휴머노이드의 진짜 시험",
      "channel": "안될공학 - IT 테크 신기술",
      "publishedAt": "2026-05-14T14:19:34Z",
      "viewCount": 43265
    }
  ],
  "collected_at": "2026-05-15T14:10:57Z"
}